simber/__init__.py
simber/colors.py
simber/configurations.py
simber/exceptions.py
simber/formatter.py
simber/logger.py
simber/stream.py
simber-0.2.6.dist-info/LICENSE
simber-0.2.6.dist-info/METADATA
simber-0.2.6.dist-info/WHEEL
simber-0.2.6.dist-info/top_level.txt
simber-0.2.6.dist-info/RECORD
