Metadata-Version: 2.1
Name: simber
Version: 0.2.6
Summary: Simple, minimal, powerful logging library for Python
Home-page: https://github.com/deepjyoti30/simber
Author: Deepjyoti Barman
Author-email: deep.barma30@gmail.com
Classifier: Programming Language :: Python :: 3
Classifier: License :: OSI Approved :: MIT License
Classifier: Operating System :: OS Independent
Requires-Python: >=3
License-File: LICENSE
